[{
    "id": 1,
    "quote": "That'll be our little secret."
  },
  {
    "id": 2,
    "quote": "Any way you want it to be, that's just right."
  },
  {
    "id": 3,
    "quote": "There are no mistakes, just happy accidents."
  },
  {
    "id": 4,
    "quote": "Maybe in our world there lives a happy little tree over there."
  },
  {
    "id": 5,
    "quote": "You know me, I gotta put in a big tree."
  },
  {
    "id": 6,
    "quote": "Here's your bravery test!"
  },
  {
    "id": 7,
    "quote": "Gotta give him a friend. Like I always say 'everyone needs a friend.'"
  },
  {
    "id": 8,
    "quote": "That's a crooked tree. We'll send him to Washington."
  },
  {
    "id": 9,
    "quote": "There's nothing wrong with having a tree as a friend."
  },
  {
    "id": 10,
    "quote": "I can't go over 30 minutes, because we have a mean ol' director with no sense of humor."
  }
]